<annotation>
	<folder>untitled folder</folder>
	<filename>10x_5.jpg</filename>
	<path>/Users/michaelcao/Desktop/research/2.20 tensorflow/untitled folder/10x_5.jpg</path>
	<source>
		<database>Unknown</database>
	</source>
	<size>
		<width>2048</width>
		<height>1088</height>
		<depth>1</depth>
	</size>
	<segmented>0</segmented>
	<object>
		<name>square</name>
		<pose>Unspecified</pose>
		<truncated>0</truncated>
		<difficult>0</difficult>
		<bndbox>
			<xmin>868</xmin>
			<ymin>231</ymin>
			<xmax>927</xmax>
			<ymax>293</ymax>
		</bndbox>
	</object>
	<object>
		<name>square</name>
		<pose>Unspecified</pose>
		<truncated>0</truncated>
		<difficult>0</difficult>
		<bndbox>
			<xmin>1337</xmin>
			<ymin>442</ymin>
			<xmax>1388</xmax>
			<ymax>489</ymax>
		</bndbox>
	</object>
	<object>
		<name>square</name>
		<pose>Unspecified</pose>
		<truncated>0</truncated>
		<difficult>0</difficult>
		<bndbox>
			<xmin>1377</xmin>
			<ymin>849</ymin>
			<xmax>1452</xmax>
			<ymax>936</ymax>
		</bndbox>
	</object>
	<object>
		<name>square</name>
		<pose>Unspecified</pose>
		<truncated>0</truncated>
		<difficult>0</difficult>
		<bndbox>
			<xmin>230</xmin>
			<ymin>61</ymin>
			<xmax>274</xmax>
			<ymax>101</ymax>
		</bndbox>
	</object>
	<object>
		<name>square</name>
		<pose>Unspecified</pose>
		<truncated>0</truncated>
		<difficult>0</difficult>
		<bndbox>
			<xmin>1087</xmin>
			<ymin>115</ymin>
			<xmax>1120</xmax>
			<ymax>140</ymax>
		</bndbox>
	</object>
	<object>
		<name>square</name>
		<pose>Unspecified</pose>
		<truncated>0</truncated>
		<difficult>0</difficult>
		<bndbox>
			<xmin>1339</xmin>
			<ymin>132</ymin>
			<xmax>1369</xmax>
			<ymax>174</ymax>
		</bndbox>
	</object>
	<object>
		<name>square</name>
		<pose>Unspecified</pose>
		<truncated>0</truncated>
		<difficult>0</difficult>
		<bndbox>
			<xmin>1568</xmin>
			<ymin>51</ymin>
			<xmax>1600</xmax>
			<ymax>87</ymax>
		</bndbox>
	</object>
	<object>
		<name>square</name>
		<pose>Unspecified</pose>
		<truncated>0</truncated>
		<difficult>0</difficult>
		<bndbox>
			<xmin>667</xmin>
			<ymin>344</ymin>
			<xmax>702</xmax>
			<ymax>388</ymax>
		</bndbox>
	</object>
	<object>
		<name>square</name>
		<pose>Unspecified</pose>
		<truncated>0</truncated>
		<difficult>0</difficult>
		<bndbox>
			<xmin>570</xmin>
			<ymin>580</ymin>
			<xmax>598</xmax>
			<ymax>606</ymax>
		</bndbox>
	</object>
	<object>
		<name>square</name>
		<pose>Unspecified</pose>
		<truncated>0</truncated>
		<difficult>0</difficult>
		<bndbox>
			<xmin>1146</xmin>
			<ymin>528</ymin>
			<xmax>1179</xmax>
			<ymax>554</ymax>
		</bndbox>
	</object>
	<object>
		<name>square</name>
		<pose>Unspecified</pose>
		<truncated>0</truncated>
		<difficult>0</difficult>
		<bndbox>
			<xmin>1415</xmin>
			<ymin>270</ymin>
			<xmax>1442</xmax>
			<ymax>291</ymax>
		</bndbox>
	</object>
	<object>
		<name>square</name>
		<pose>Unspecified</pose>
		<truncated>0</truncated>
		<difficult>0</difficult>
		<bndbox>
			<xmin>183</xmin>
			<ymin>120</ymin>
			<xmax>213</xmax>
			<ymax>158</ymax>
		</bndbox>
	</object>
	<object>
		<name>square</name>
		<pose>Unspecified</pose>
		<truncated>0</truncated>
		<difficult>0</difficult>
		<bndbox>
			<xmin>1590</xmin>
			<ymin>459</ymin>
			<xmax>1616</xmax>
			<ymax>492</ymax>
		</bndbox>
	</object>
</annotation>
